pyburg/Tree.py
pyburg/__init__.py
pyburg/brg2py.py
pyburg/postfix.py
pyburg/pyburg.py
pyburg/strbuf.py
pyburg-1.4.2.dist-info/licenses/LICENSE
pyburg-1.4.2.dist-info/METADATA
pyburg-1.4.2.dist-info/WHEEL
pyburg-1.4.2.dist-info/top_level.txt
pyburg-1.4.2.dist-info/RECORD
