Metadata-Version: 2.4
Name: pyburg
Version: 1.4.2
Summary: A BURG (Bottom-Up Rewrite Grammar) instruction selection compiler generator
Home-page: https://github.com/pedroreissantos/pyburg
Author: Pedro Reis dos Santos
Author-email: reis.santos@tecnico.ulisboa.pt
License: MIT
Classifier: Programming Language :: Python :: 3
Classifier: License :: OSI Approved :: MIT License
Classifier: Operating System :: OS Independent
Classifier: Intended Audience :: Developers
Classifier: Topic :: Software Development :: Compilers
Classifier: Development Status :: 3 - Alpha
Classifier: Environment :: Console
Requires-Python: >=3.6
License-File: LICENSE
Requires-Dist: ply
Dynamic: author
Dynamic: author-email
Dynamic: classifier
Dynamic: description
Dynamic: home-page
Dynamic: license
Dynamic: license-file
Dynamic: requires-dist
Dynamic: requires-python
Dynamic: summary
